arcanechat_tui/__init__.py
arcanechat_tui/__main__.py
arcanechat_tui/_version.py
arcanechat_tui/application.py
arcanechat_tui/cards_widget.py
arcanechat_tui/chatlist.py
arcanechat_tui/cli.py
arcanechat_tui/composer.py
arcanechat_tui/container.py
arcanechat_tui/conversation.py
arcanechat_tui/eventcenter.py
arcanechat_tui/lazylistwaker.py
arcanechat_tui/logger.py
arcanechat_tui/main.py
arcanechat_tui/util.py
arcanechat_tui/welcome_widget.py
arcanechat_tui-0.11.1.dist-info/LICENSE
arcanechat_tui-0.11.1.dist-info/METADATA
arcanechat_tui-0.11.1.dist-info/WHEEL
arcanechat_tui-0.11.1.dist-info/entry_points.txt
arcanechat_tui-0.11.1.dist-info/top_level.txt
arcanechat_tui-0.11.1.dist-info/RECORD
