Metadata-Version: 2.2
Name: arcanechat-tui
Version: 0.11.1
Summary: ArcaneChat client for the command line
Author-email: adbenitez <adb@merlinux.eu>
Project-URL: Homepage, https://github.com/ArcaneChat/arcanechat-tui
Project-URL: Issues, https://github.com/ArcaneChat/arcanechat-tui/issues
Keywords: deltachat,ncurses,tui,arcanechat
Classifier: Development Status :: 4 - Beta
Classifier: Intended Audience :: End Users/Desktop
Classifier: License :: OSI Approved :: GNU General Public License v3 (GPLv3)
Classifier: Operating System :: POSIX
Classifier: Programming Language :: Python :: 3
Requires-Python: >=3.8
License-File: LICENSE
Requires-Dist: deltachat2>=0.2.0
Requires-Dist: urwid>=2.6.10
Requires-Dist: urwid-readline>=0.14
Requires-Dist: appdirs>=1.4.4
Provides-Extra: full
Requires-Dist: deltachat-rpc-server>=1.136.6; extra == "full"
Provides-Extra: dev
Requires-Dist: deltachat-rpc-server; extra == "dev"
Requires-Dist: black; extra == "dev"
Requires-Dist: mypy; extra == "dev"
Requires-Dist: isort; extra == "dev"
Requires-Dist: pylint; extra == "dev"
Requires-Dist: pylama; extra == "dev"
Requires-Dist: pytest; extra == "dev"
